gnss_tec/__init__.py
gnss_tec/dtutils.py
gnss_tec/glo.py
gnss_tec/gnss.py
gnss_tec/nav.py
gnss_tec/rinex.py
gnss_tec/tec.py
gnss_tec-1.1.1.dist-info/LICENSE.txt
gnss_tec-1.1.1.dist-info/METADATA
gnss_tec-1.1.1.dist-info/WHEEL
gnss_tec-1.1.1.dist-info/top_level.txt
gnss_tec-1.1.1.dist-info/RECORD
