Metadata-Version: 2.1
Name: gnss-tec
Version: 1.1.1
Summary: Total electron content reconstruction using GNSS data
Home-page: https://github.com/gnss-lab/gnss-tec
Author: Ilya Zhivetiev
Author-email: i.zhivetiev@gnss-lab.org
License: MIT
Keywords: ionosphere gnss tec development
Platform: UNKNOWN
Classifier: Development Status :: 4 - Beta
Classifier: Intended Audience :: Science/Research
Classifier: Intended Audience :: Developers
Classifier: Topic :: Software Development
Classifier: Topic :: Scientific/Engineering
Classifier: License :: OSI Approved :: MIT License
Classifier: Programming Language :: Python :: 3
Classifier: Programming Language :: Python :: 3.3
Classifier: Programming Language :: Python :: 3.4
Classifier: Programming Language :: Python :: 3.5
Classifier: Programming Language :: Python :: 3.6
Requires-Python: >=3
Provides-Extra: test
Requires-Dist: pytest ; extra == 'test'
Requires-Dist: coverage ; extra == 'test'
